PyNeuro/PyNeuro.py
PyNeuro/__init__.py
PyNeuro-1.3.1.dist-info/LICENSE
PyNeuro-1.3.1.dist-info/METADATA
PyNeuro-1.3.1.dist-info/WHEEL
PyNeuro-1.3.1.dist-info/top_level.txt
PyNeuro-1.3.1.dist-info/RECORD
